az_envs/__init__.py
az_envs/cli.py
az_envs/env_file.py
az_envs/exceptions.py
az_envs/keyvault.py
az_envs-0.1.2.dist-info/METADATA
az_envs-0.1.2.dist-info/WHEEL
az_envs-0.1.2.dist-info/entry_points.txt
az_envs-0.1.2.dist-info/top_level.txt
az_envs-0.1.2.dist-info/RECORD
