Metadata-Version: 2.4
Name: az-envs
Version: 0.1.2
Summary: Create .env files from Azure Key Vault secrets
Author: Dillon Johnson
License: MIT
Requires-Python: >=3.9
Requires-Dist: azure-identity>=1.15.0
Requires-Dist: azure-keyvault-secrets>=4.7.0
Requires-Dist: azure-mgmt-keyvault>=10.0.0
Requires-Dist: click>=8.0.0
Provides-Extra: dev
Requires-Dist: pytest>=7.0.0; extra == "dev"
Requires-Dist: ruff>=0.1.0; extra == "dev"
